{
  "cached_at": "2025-11-26T12:21:26.167189",
  "data": {
    "competitors": [
      {
        "Competitor_Name": "Hertz",
        "Competitor_Price": 490,
        "Competitor_Category": "Full-size SUV",
        "Date": "2025-11-26 12:21",
        "Source": "Live Market Intelligence",
        "Confidence": 95
      },
      {
        "Competitor_Name": "Budget",
        "Competitor_Price": 480,
        "Competitor_Category": "Full-size SUV",
        "Date": "2025-11-26 12:21",
        "Source": "Live Market Intelligence",
        "Confidence": 95
      },
      {
        "Competitor_Name": "Thrifty",
        "Competitor_Price": 475,
        "Competitor_Category": "Full-size SUV",
        "Date": "2025-11-26 12:21",
        "Source": "Live Market Intelligence",
        "Confidence": 95
      }
    ],
    "avg_price": 481.6666666666667,
    "competitor_count": 3,
    "last_updated": "2025-11-26T12:21:26.166189",
    "location": "Medina Downtown",
    "category": "SUV Large",
    "is_live": true
  }
}